{"description":"Deployment Options: How To Ship New Code Without Taking Your System Down\n\nErlang is quite famous for long-running interruption-free installations. But how is this achieved in practice while still evolving the software?\n\nWe will look at different deployment options, from simple to advanced:\n\n1. Deployment by restart\n\n2. Hot code reloading\n\n3. Release handling\n\nSee hot code reloading in action and learn how to avoid common traps & pitfalls.\n\nTalk objectives: By the end of this talk you shall be able to decide: Which strategy is right for me? What do I have to consider?\n\nTarget audience: General familiarity with Erlang is assumed.","id":"ae25b39a-de5c-4f4a-b2c8-bf89d1a0b751","meta":{"duration":"PT32M47S"},"presenter":{"name":null},"slug":"martin-rehfeld-how-to-ship-new-code-without-taking-your-system-down-berlin-erlang-factory-lite","source":{"id":"NfCLCmRi4_Y","provider":"youtube"},"tag":["Erlang","Martin Rehfeld","Deployment Options"],"title":"Martin Rehfeld - How To Ship New Code Without Taking Your System Down -  Berlin Erlang Factory Lite","thumbnails":{"default":{"url":"https://i.ytimg.com/vi/NfCLCmRi4_Y/default.jpg","width":120,"height":90},"medium":{"url":"https://i.ytimg.com/vi/NfCLCmRi4_Y/mqdefault.jpg","width":320,"height":180},"high":{"url":"https://i.ytimg.com/vi/NfCLCmRi4_Y/hqdefault.jpg","width":480,"height":360}}}